{
  "Name": "ItemTiamatCleave",
  "AlternateName": null,
  "AnimationName": "Attack1",
  "MissileSpeed": 0.0,
  "LineWidth": 0.0,
  "CastFrame": 11.395,
  "AIRange": 0.0,
  "CastRange": 325.0,
  "CastRadius": 325.0,
  "Cooldown": 7.0,
  "Cooldown1": 7.0,
  "Cooldown2": 7.0,
  "Cooldown3": 7.0,
  "Cooldown4": 7.0,
  "Cooldown5": 7.0,
  "Cooldown6": 0.0,
  "DelayCastOffsetPercent": -0.5,
  "SpellFlags": 262144,
  "TextFlags": "AffectEnemies | AffectNeutral | AffectMinions | AffectHeroes",
  "HitEffectName": "akali_shadowSwipe_tar,troy"
}