{
  "Name": "KarthusLayWasteA1",
  "AlternateName": "KarthusLayWasteA1",
  "AnimationName": "Spell1_a",
  "MissileSpeed": 20.0,
  "LineWidth": 0.0,
  "CastFrame": 20.0,
  "AIRange": 0.0,
  "CastRange": 875.0,
  "CastRadius": 160.0,
  "Cooldown": 1.0,
  "Cooldown1": 1.0,
  "Cooldown2": 1.0,
  "Cooldown3": 1.0,
  "Cooldown4": 1.0,
  "Cooldown5": 1.0,
  "Cooldown6": 0.0,
  "DelayCastOffsetPercent": 0.0,
  "SpellFlags": 511008,
  "TextFlags": "AffectEnemies | AffectFriends | AffectNeutral | AffectMinions | AffectHeroes | AffectTurrets | AlwaysSelf",
  "HitEffectName": ""
}