{
  "Name": "VolibearW",
  "AlternateName": "VolibearW",
  "AnimationName": "Spell2",
  "MissileSpeed": 1450.0,
  "LineWidth": 0.0,
  "CastFrame": 7.5,
  "AIRange": 0.0,
  "CastRange": 400.0,
  "CastRadius": 550.0,
  "Cooldown": 18.0,
  "Cooldown1": 18.0,
  "Cooldown2": 18.0,
  "Cooldown3": 18.0,
  "Cooldown4": 18.0,
  "Cooldown5": 18.0,
  "Cooldown6": 0.0,
  "DelayCastOffsetPercent": -0.5,
  "SpellFlags": 115712,
  "TextFlags": "AffectEnemies | AffectNeutral | AffectMinions | AffectHeroes",
  "HitEffectName": "AnnieBasicAttack_mis,troy"
}