{"Id":0,"Name":"SRU_SnailSpawner","BaseHp":1.0,"BaseMp":0.0,"BaseMovementSpeed":450,"AbilityPowerIncPerLevel":0,"ArmorPerLevel":0.0,"AttackRange":100,"AttackSpeedPerLevel":0.0,"BaseAbilityPower":0,"BaseCritChance":25.0,"BaseDamage":8.0,"CritPerLevel":0.0,"DamagePerLevel":0.0,"HpPerLevel":0.0,"HpRegenPerLevel":0.0,"IsMelee":false,"MpPerLevel":0.0,"MPRegenPerLevel":0.0,"BaseArmor":6.0,"BaseMagicResist":0.0,"BaseHpRegen":0.0,"BaseMpRegen":0.0,"MagicResistPerLevel":0.0,"AttackDelayOffsetPercent":-0.05,"BaseDodge":0.0,"BaseAttackSpeed":1.5,"SelectionHeight":100.0,"SelectionRadius":115.0}